{
  "id": "https://ror.org/00d22z552",
  "name": "Institut für Qualitätssicherung von Stoffsystemen Freiberg",
  "types": [
    "Facility"
  ],
  "links": [
    "http://www.iqs-freiberg.com/index.php/en/"
  ],
  "aliases": [],
  "acronyms": [
    "IQS"
  ],
  "status": "active",
  "wikipedia_url": "",
  "labels": [],
  "email_address": null,
  "ip_addresses": [],
  "established": 1996,
  "country": {
    "country_code": "DE",
    "country_name": "Germany"
  },
  "relationships": [],
  "addresses": [
    {
      "line": null,
      "lat": 50.928563,
      "lng": 13.338138,
      "postcode": null,
      "primary": false,
      "city": "Freiberg",
      "state": null,
      "state_code": null,
      "country_geonames_id": 2921044,
      "geonames_city": {
        "id": 2925192,
        "city": "Freiberg",
        "nuts_level1": {
          "code": "DED",
          "name": "SACHSEN"
        },
        "nuts_level2": {
          "code": "DED4",
          "name": "Chemnitz"
        },
        "nuts_level3": {
          "code": "DED43",
          "name": "Mittelsachsen"
        },
        "geonames_admin1": {
          "id": 2842566,
          "name": "Saxony",
          "ascii_name": "Saxony",
          "code": "DE.13"
        },
        "geonames_admin2": {
          "id": null,
          "name": null,
          "ascii_name": null,
          "code": null
        },
        "license": {
          "attribution": "Data from geonames.org under a CC-BY 3.0 license",
          "license": "http://creativecommons.org/licenses/by/3.0/"
        }
      }
    }
  ],
  "external_ids": {
    "GRID": {
      "preferred": "grid.506365.3",
      "all": "grid.506365.3"
    }
  }
}
