{
  "locations": [
    {
      "geonames_id": 2940132,
      "geonames_details": {
        "country_code": "DE",
        "country_name": "Germany",
        "lat": 50.825513,
        "lng": 12.93162,
        "name": "Chemnitz"
      }
    }
  ],
  "established": 1993,
  "external_ids": [
    {
      "type": "grid",
      "all": [
        "grid.438610.8"
      ],
      "preferred": "grid.438610.8"
    },
    {
      "type": "wikidata",
      "all": [
        "Q30292282"
      ],
      "preferred": null
    }
  ],
  "id": "https://ror.org/00nk1fh63",
  "domains": [],
  "links": [
    {
      "type": "website",
      "value": "https://www.tbz-pariv.de/"
    }
  ],
  "names": [
    {
      "value": "TBZ PARIV (Germany)",
      "types": [
        "ror_display",
        "label"
      ],
      "lang": null
    }
  ],
  "relationships": [],
  "status": "active",
  "types": [
    "company"
  ],
  "admin": {
    "created": {
      "date": "2018-11-14",
      "schema_version": "1.0"
    },
    "last_modified": {
      "date": "2021-03-17",
      "schema_version": "1.0"
    }
  }
}
