{
  "locations": [
    {
      "geonames_id": 2935022,
      "geonames_details": {
        "country_code": "DE",
        "country_name": "Germany",
        "lat": 51.014335,
        "lng": 13.754917,
        "name": "Dresden"
      }
    }
  ],
  "established": null,
  "external_ids": [
    {
      "type": "grid",
      "all": [
        "grid.506517.0"
      ],
      "preferred": "grid.506517.0"
    }
  ],
  "id": "https://ror.org/01drpqr75",
  "domains": [],
  "links": [
    {
      "type": "website",
      "value": "https://www.tzdresden.de"
    }
  ],
  "names": [
    {
      "value": "TZS",
      "types": [
        "acronym"
      ],
      "lang": null
    },
    {
      "value": "Technologiezentrum Dresden (Germany)",
      "types": [
        "ror_display",
        "label"
      ],
      "lang": null
    }
  ],
  "relationships": [],
  "status": "active",
  "types": [
    "company"
  ],
  "admin": {
    "created": {
      "date": "2019-11-07",
      "schema_version": "1.0"
    },
    "last_modified": {
      "date": "2021-03-17",
      "schema_version": "1.0"
    }
  }
}
