{
  "locations": [
    {
      "geonames_id": 2879139,
      "geonames_details": {
        "country_code": "DE",
        "country_name": "Germany",
        "lat": 51.33962,
        "lng": 12.37129,
        "name": "Leipzig"
      }
    }
  ],
  "established": 1995,
  "external_ids": [
    {
      "type": "grid",
      "all": [
        "grid.505969.6"
      ],
      "preferred": "grid.505969.6"
    },
    {
      "type": "isni",
      "all": [
        "0000 0001 2168 0824"
      ],
      "preferred": "0000 0001 2168 0824"
    }
  ],
  "id": "https://ror.org/04tjfqn96",
  "domains": [],
  "links": [
    {
      "type": "website",
      "value": "https://leibniz-gwzo.de/de"
    }
  ],
  "names": [
    {
      "value": "GWZO",
      "types": [
        "acronym"
      ],
      "lang": null
    },
    {
      "value": "Geisteswissenschaftliches Zentrum Geschichte und Kultur Ostmitteleuropas",
      "types": [
        "alias"
      ],
      "lang": null
    },
    {
      "value": "Leibniz Institute for the History and Culture of Eastern Europe (GWZO)",
      "types": [
        "ror_display",
        "label"
      ],
      "lang": null
    },
    {
      "value": "Leibniz-Institut für Geschichte und Kultur des östlichen Europa (GWZO)",
      "types": [
        "label"
      ],
      "lang": "de"
    }
  ],
  "relationships": [
    {
      "label": "Leibniz Association",
      "type": "parent",
      "id": "https://ror.org/01n6r0e97"
    }
  ],
  "status": "active",
  "types": [
    "other"
  ],
  "admin": {
    "created": {
      "date": "2019-05-06",
      "schema_version": "1.0"
    },
    "last_modified": {
      "date": "2022-11-15",
      "schema_version": "1.0"
    }
  }
}
