{
  "locations": [
    {
      "geonames_id": 2935022,
      "geonames_details": {
        "continent_code": "EU",
        "continent_name": "Europe",
        "country_code": "DE",
        "country_name": "Germany",
        "country_subdivision_code": "SN",
        "country_subdivision_name": "Saxony",
        "lat": 51.05089,
        "lng": 13.73832,
        "name": "Dresden"
      }
    }
  ],
  "established": null,
  "external_ids": [
    {
      "type": "grid",
      "all": [
        "grid.506398.1"
      ],
      "preferred": "grid.506398.1"
    }
  ],
  "id": "https://ror.org/0527w8j59",
  "domains": [],
  "links": [
    {
      "type": "website",
      "value": "https://www.itwh.de/de/"
    }
  ],
  "names": [
    {
      "value": "Institut für technisch-wissenschaftliche Hydrologie",
      "types": [
        "label"
      ],
      "lang": "de"
    },
    {
      "value": "Institute for Technical and Scientific Hydrology (Germany)",
      "types": [
        "ror_display",
        "label"
      ],
      "lang": null
    },
    {
      "value": "itwh",
      "types": [
        "acronym"
      ],
      "lang": null
    }
  ],
  "relationships": [],
  "status": "active",
  "types": [
    "company"
  ],
  "admin": {
    "created": {
      "date": "2019-11-07",
      "schema_version": "1.0"
    },
    "last_modified": {
      "date": "2024-12-11",
      "schema_version": "2.1"
    }
  }
}
